nafig/__init__.py
nafig/plots.py
nafig/utils.py
nafig-1.0.1.dist-info/LICENSE
nafig-1.0.1.dist-info/METADATA
nafig-1.0.1.dist-info/WHEEL
nafig-1.0.1.dist-info/RECORD
