Metadata-Version: 2.1
Name: nafig
Version: 1.0.1
Summary: Package for creating figures with NA data distribution
Home-page: https://github.com/VladimirShitov/nafig
License: MIT
Author: vladimirshitov98
Author-email: vladimirshitov98@gmail.com
Requires-Python: >=3.9,<4.0
Classifier: Development Status :: 3 - Alpha
Classifier: Intended Audience :: Developers
Classifier: License :: OSI Approved :: MIT License
Classifier: Operating System :: OS Independent
Classifier: Programming Language :: Python :: 3
Classifier: Programming Language :: Python :: 3.9
Classifier: Programming Language :: Python :: 3.10
Classifier: Programming Language :: Python :: 3.11
Classifier: Programming Language :: Python :: 3
Classifier: Programming Language :: Python :: 3.9
Classifier: Topic :: Software Development :: Libraries :: Python Modules
Requires-Dist: click (==8.0.2)
Requires-Dist: matplotlib (>=3.7.1,<4.0.0)
Requires-Dist: seaborn (>=0.12.2,<0.13.0)
Project-URL: Repository, https://github.com/VladimirShitov/nafig
